MANIFEST.in
README.txt
setup.cfg
setup.py
docs/HISTORY.txt
pcommerce/__init__.py
pcommerce.multilanguagefields.egg-info/PKG-INFO
pcommerce.multilanguagefields.egg-info/SOURCES.txt
pcommerce.multilanguagefields.egg-info/dependency_links.txt
pcommerce.multilanguagefields.egg-info/entry_points.txt
pcommerce.multilanguagefields.egg-info/namespace_packages.txt
pcommerce.multilanguagefields.egg-info/not-zip-safe
pcommerce.multilanguagefields.egg-info/requires.txt
pcommerce.multilanguagefields.egg-info/top_level.txt
pcommerce/multilanguagefields/__init__.py
pcommerce/multilanguagefields/configure.zcml
pcommerce/multilanguagefields/extender.py
pcommerce/multilanguagefields/fields.py
pcommerce/multilanguagefields/setuphandlers.py
pcommerce/multilanguagefields/widget.py
pcommerce/multilanguagefields/Extensions/Install.py
pcommerce/multilanguagefields/Extensions/__init__.py
pcommerce/multilanguagefields/profiles/default/catalog.xml
pcommerce/multilanguagefields/profiles/default/metadata.xml
pcommerce/multilanguagefields/profiles/default/pcommerce.multilanguagefields_install.txt
pcommerce/multilanguagefields/profiles/default/skins.xml
pcommerce/multilanguagefields/profiles/uninstall/import_steps.xml
pcommerce/multilanguagefields/profiles/uninstall/pcommerce.multilanguagefields_uninstall.txt
pcommerce/multilanguagefields/profiles/uninstall/skins.xml
pcommerce/multilanguagefields/skins/pcommerce_multilanguagefields/multilanguage_singlekeyword.pt